examples/basic_usage/__init__.py
examples/basic_usage/basic_usage_example.py
examples/basic_usage/example_utils.py
examples/other_decorators_interaction/__init__.py
examples/other_decorators_interaction/other_decorators.py
examples/other_decorators_interaction/other_decorators_interaction_example.py
examples/tldr/__init__.py
examples/tldr/tldr_example.py
vardef/__init__.py
vardef-0.1.0.dist-info/AUTHORS.rst
vardef-0.1.0.dist-info/LICENSE
vardef-0.1.0.dist-info/METADATA
vardef-0.1.0.dist-info/WHEEL
vardef-0.1.0.dist-info/top_level.txt
vardef-0.1.0.dist-info/RECORD
